manageiq_client/__init__.py
manageiq_client/api.py
manageiq_client/filters.py
manageiq_client/utils.py
manageiq_client-0.6.1.dist-info/COPYING
manageiq_client-0.6.1.dist-info/METADATA
manageiq_client-0.6.1.dist-info/WHEEL
manageiq_client-0.6.1.dist-info/top_level.txt
manageiq_client-0.6.1.dist-info/RECORD
