Metadata-Version: 2.1
Name: manageiq-client
Version: 0.6.1
Summary: Python client for the ManageIQ REST-API
Home-page: https://github.com/ManageIQ/manageiq-api-client-python
Author: Milan Falesnik
Author-email: mfalesni@redhat.com
License: GPLv2
Keywords: api,rest,client,manageiq
Platform: UNKNOWN
Classifier: Topic :: Utilities
Classifier: License :: OSI Approved :: GNU General Public License v2 (GPLv2)
Classifier: Topic :: Software Development :: Libraries :: Python Modules
Classifier: Programming Language :: Python :: 2.7
Classifier: Programming Language :: Python :: 3.4
Classifier: Programming Language :: Python :: 3.5
Classifier: Programming Language :: Python :: 3.6
Classifier: Programming Language :: Python :: 3.7
Classifier: Intended Audience :: Developers
Classifier: Development Status :: 3 - Alpha
Requires-Dist: requests
Requires-Dist: iso8601
Requires-Dist: simplejson
Requires-Dist: six
Requires-Dist: wait-for
